sidekick/__init__.py
sidekick/_modules.py
sidekick/_operators.py
sidekick/_toolz.py
sidekick/_utils.py
sidekick/api.py
sidekick/conftest.py
sidekick/evil.py
sidekick/op.py
sidekick/pred.py
sidekick/properties.py
sidekick/py.type
sidekick/typing.py
sidekick/beta/__init__.py
sidekick/cache/__init__.py
sidekick/collections/__init__.py
sidekick/collections/frozendict.py
sidekick/collections/invmap.py
sidekick/collections/lazylist.py
sidekick/collections/tree/__init__.py
sidekick/collections/tree/children.py
sidekick/collections/tree/io.py
sidekick/collections/tree/node_base.py
sidekick/collections/tree/node_classes.py
sidekick/collections/tree/node_iterators.py
sidekick/collections/tree/node_sexpr.py
sidekick/collections/tree/render.py
sidekick/collections/tree/resolver.py
sidekick/collections/tree/transform.py
sidekick/collections/tree/util.py
sidekick/contrib/__init__.py
sidekick/contrib/json.py
sidekick/contrib/render.py
sidekick/experimental/__init__.py
sidekick/experimental/builtins.py
sidekick/experimental/cached_dict.py
sidekick/experimental/case_syntax.py
sidekick/experimental/coro.py
sidekick/experimental/function_dispatch.py
sidekick/experimental/functions.py
sidekick/experimental/idmap.py
sidekick/experimental/inspection.py
sidekick/experimental/iterators.py
sidekick/experimental/linkedlist.py
sidekick/experimental/maptools.py
sidekick/experimental/math.py
sidekick/experimental/misc.py
sidekick/experimental/nested.py
sidekick/experimental/observableseq.py
sidekick/experimental/queue.py
sidekick/experimental/streams.py
sidekick/experimental/tagseq.py
sidekick/experimental/text.py
sidekick/experimental/magics/__init__.py
sidekick/experimental/magics/argument_magics.py
sidekick/experimental/magics/base_magics.py
sidekick/experimental/magics/data_magics.py
sidekick/experimental/magics/list_magic.py
sidekick/functions/__init__.py
sidekick/functions/core_functions.py
sidekick/functions/fn.py
sidekick/functions/fn_mixins.py
sidekick/functions/fn_placeholders.py
sidekick-0.8.2.dist-info/LICENSE
sidekick-0.8.2.dist-info/WHEEL
sidekick-0.8.2.dist-info/METADATA
sidekick-0.8.2.dist-info/RECORD
