Metadata-Version: 2.1
Name: sidekick
Version: 0.8.2
Summary: A companion library that enhance your functional superpowers.
Home-page: http://github.com/fabiommendes/sidekick/
License: UNKNOWN
Author: Fábio Macêdo Mendes
Author-email: fabiomacedomendes@gmail.com
Requires-Python: >=3.6
Classifier: Intended Audience :: Developers
Classifier: Development Status :: 4 - Beta
Classifier: License :: OSI Approved :: MIT License
Classifier: Operating System :: OS Independent
Classifier: Programming Language :: Python
Classifier: Programming Language :: Python :: 3
Classifier: Programming Language :: Python :: 3.6
Classifier: Programming Language :: Python :: 3.7
Classifier: Programming Language :: Python :: 3.8
Classifier: Topic :: Software Development :: Libraries
Requires-Dist: toolz >= 0.10.0
Requires-Dist: flake8 ; extra == "dev"
Requires-Dist: black ; extra == "dev"
Requires-Dist: readme_renderer ; extra == "dev"
Requires-Dist: sphinx ; extra == "doc"
Requires-Dist: sphinx_rtd_theme ; extra == "doc"
Requires-Dist: hypothesis ; extra == "hypothesis"
Requires-Dist: pytest ; extra == "test"
Requires-Dist: pytest-cov ; extra == "test"
Requires-Dist: mock ; extra == "test"
Requires-Dist: hypothesis ; extra == "test"
Project-URL: Documentation, https://sidekick.readthedocs.io/en/latest/
Provides-Extra: dev
Provides-Extra: doc
Provides-Extra: hypothesis
Provides-Extra: test
